nonebot/adapters/kook/__init__.py
nonebot/adapters/kook/adapter.py
nonebot/adapters/kook/api.py
nonebot/adapters/kook/bot.py
nonebot/adapters/kook/config.py
nonebot/adapters/kook/event.py
nonebot/adapters/kook/exception.py
nonebot/adapters/kook/message.py
nonebot/adapters/kook/permission.py
nonebot/adapters/kook/utils.py
nonebot_adapter_kook-0.0.8.dist-info/LICENSE
nonebot_adapter_kook-0.0.8.dist-info/WHEEL
nonebot_adapter_kook-0.0.8.dist-info/METADATA
nonebot_adapter_kook-0.0.8.dist-info/RECORD
